xcrypt.py
xcrypt-1.2.0.dist-info/METADATA
xcrypt-1.2.0.dist-info/WHEEL
xcrypt-1.2.0.dist-info/top_level.txt
xcrypt-1.2.0.dist-info/RECORD
