Metadata-Version: 2.1
Name: xcrypt
Version: 1.2.0
Summary: A Python encryption library.
Home-page: https://github.com/kgsensei/XCrypt
Author: kgsensei
Author-email: ceojeremy@rainydais.com
License: UNKNOWN
Project-URL: Bug Tracker, https://github.com/kgsensei/XCrypt/issues
Platform: UNKNOWN
Classifier: Programming Language :: Python :: 3
Classifier: Operating System :: OS Independent
Classifier: Natural Language :: English
Classifier: Topic :: Security :: Cryptography
Requires-Python: >=3.6
